[
 {
  "id": 1,
  "firstName": "Javier",
  "lastName": "Vega",
  "email": "pcomberbeach0@mediafire.com",
  "password": "xq4Aouv",
  "type": "Admin",
  "avatar": "/images/avatars/usuario2.jpg",
  "phone": "6430200272"
 },
 {
  "id": 2,
  "firstName": "Camila",
  "lastName": "Vega",
  "email": "rrossander1@amazon.co.jp",
  "password": "9xapocbWcXQ",
  "type": "Admin",
  "avatar": "/images/avatars/usuario6.jpg",
  "phone": "6235045824"
 },
 {
  "id": 3,
  "firstName": "Carolina",
  "lastName": "Diaz",
  "email": "mscholar2@webs.com",
  "password": "ovyoh1",
  "type": "Admin",
  "avatar": "",
  "phone": "1984867601"
 },
 {
  "id": 4,
  "firstName": "Eduardo",
  "lastName": "Perez",
  "email": "ecruickshanks3@bravesites.com",
  "password": "MFqPr8Yq",
  "type": "Admin",
  "avatar": "/images/avatars/usuario2.jpg",
  "phone": "8853746238"
 },
 {
  "id": 5,
  "firstName": "Rosa",
  "lastName": "Abal",
  "email": "anarrie4@patch.com",
  "password": "A3zUMHoG",
  "type": "Admin",
  "avatar": "/images/avatars/usuario2.jpg",
  "phone": "3260242104"
 },
 {
  "id": 6,
  "firstName": "Dario",
  "lastName": "Estevez",
  "email": "bcarradice5@telegraph.co.uk",
  "password": "lSo89jxFNk",
  "type": "Users",
  "avatar": "/images/avatars/usuario3.jpg",
  "phone": "8226537924"
 },
 {
  "id": 7,
  "firstName": "Jorge",
  "lastName": "Rodriguez",
  "email": "lflanigan6@google.es",
  "password": "KjSj3nc0hn8c",
  "type": "Users",
  "avatar": "/images/avatars/usuario4.jpg",
  "phone": "8847403383"
 },
 {
  "id": 8,
  "firstName": "Tatiana",
  "lastName": "Gomez",
  "email": "hwinstanley7@unicef.org",
  "password": "oXahsu",
  "type": "Admin",
  "avatar": "",
  "phone": "8119184947"
 },
 {
  "id": 9,
  "firstName": "Javier",
  "lastName": "Oliva",
  "email": "ifricker8@nps.gov",
  "password": "tHubLbce",
  "type": "Users",
  "avatar": "/images/avatars/usuario3.jpg",
  "phone": "3683855096"
 },
 {
  "id": 10,
  "firstName": "Jimena",
  "lastName": "Estevez",
  "email": "dgrassick9@arizona.edu",
  "password": "x4WobgpY",
  "type": "Users",
  "avatar": "/images/avatars/usuario3.jpg",
  "phone": "7035642161"
 },
 {
  "id": 11,
  "firstName": "Rodrigo",
  "lastName": "Ponti",
  "email": "dwheara@ezinearticles.com",
  "password": "T0Wumbhxj",
  "type": "Users",
  "avatar": "/images/avatars/usuario2.jpg",
  "phone": "6864851621"
 },
 {
  "id": 12,
  "firstName": "Camila",
  "lastName": "Vega",
  "email": "srosebothamb@netscape.com",
  "password": "FlwqQZi",
  "type": "Users",
  "avatar": "/images/avatars/usuario4.jpg",
  "phone": "0668585188"
 },
 {
  "id": 13,
  "firstName": "Rodrigo",
  "lastName": "Prieto",
  "email": "mrazouxc@irs.gov",
  "password": "7QjOjVe9",
  "type": "Admin",
  "avatar": "/images/avatars/usuario6.jpg",
  "phone": "2113447665"
 },
 {
  "id": 14,
  "firstName": "Carolina",
  "lastName": "Gomez",
  "email": "pchrismasd@acquirethisname.com",
  "password": "94rlQqUK1",
  "type": "Users",
  "avatar": "/images/avatars/usuario1.jpg",
  "phone": "8066170424"
 },
 {
  "id": 15,
  "firstName": "Javier",
  "lastName": "Abal",
  "email": "bferrymane@tmall.com",
  "password": "5zaIeZAg",
  "type": "Admin",
  "avatar": "",
  "phone": "7146336859"
 }
]